youscribe/__init__.py
youscribe/_version.py
youscribe/main.py
youscribe/models.py
youscribe/scraper.py
youscribe/transcriber.py
youscribe/transcript.py
youscribe-0.0.3.dist-info/METADATA
youscribe-0.0.3.dist-info/WHEEL
youscribe-0.0.3.dist-info/top_level.txt
youscribe-0.0.3.dist-info/RECORD
