Metadata-Version: 2.1
Name: youscribe
Version: 0.0.3
Summary: Library to transcribe YouTube videos using Whisper model
Author: Digital Observatory
Author-email: digitalobservatory@qut.edu.au
Classifier: Development Status :: 4 - Beta
Classifier: Programming Language :: Python :: 3.10
Classifier: Programming Language :: Python :: 3.11
Requires-Python: >=3.10
Requires-Dist: faster-whisper >=0.10.0
Requires-Dist: beautifulsoup4 >=4.12.2
Requires-Dist: requests >=2.31.0
Requires-Dist: yt-dlp >=2024.03.10
